{
  "NGJF2600100": {
    "actual_etd": "2026-06-18",
    "vessel_name": "HEUNG-A AKITA 2621N",
    "carrier": "DONG YOUNG",
    "pol": "NAGOYA",
    "scheduled_etd": "2026-06-16",
    "confirmed": false,
    "updated_at": "2026-06-15 04:36"
  },
  "SNKO0040260600193": {
    "actual_etd": "2026-06-19",
    "vessel_name": "HEUNG-A HAIPHONG 2623W",
    "carrier": "SINOKOR",
    "pol": "ISHIKARI",
    "scheduled_etd": "2026-06-17",
    "confirmed": false,
    "note": "OMIT→2623W",
    "updated_at": "2026-06-15 04:36"
  },
  "I272245289": {
    "actual_etd": "2026-06-19",
    "vessel_name": "YM INCREMENT 329S",
    "carrier": "YANGMING",
    "pol": "TOKYO",
    "scheduled_etd": "2026-06-19",
    "confirmed": false,
    "updated_at": "2026-06-15 04:36"
  },
  "I272245291": {
    "actual_etd": "2026-06-19",
    "vessel_name": "YM INCREMENT 329S",
    "carrier": "YANGMING",
    "pol": "TOKYO",
    "scheduled_etd": "2026-06-19",
    "confirmed": false,
    "updated_at": "2026-06-15 04:36"
  },
  "I272245659": {
    "actual_etd": "2026-06-19",
    "vessel_name": "YM INCREMENT 329S",
    "carrier": "YANGMING",
    "pol": "TOKYO",
    "scheduled_etd": "2026-06-19",
    "confirmed": false,
    "updated_at": "2026-06-15 04:36"
  }
}